deflake/__init__.py
deflake/cli.py
deflake/deflake.py
deflake-0.1.2.dist-info/top_level.txt
deflake-0.1.2.dist-info/METADATA
deflake-0.1.2.dist-info/entry_points.txt
deflake-0.1.2.dist-info/DESCRIPTION.rst
deflake-0.1.2.dist-info/metadata.json
deflake-0.1.2.dist-info/WHEEL
deflake-0.1.2.dist-info/RECORD
