Metadata-Version: 2.0
Name: deflake
Version: 0.1.2
Summary: Helps debug a non determinate test (or any flaky program) by running it until it exits with a non-zero exit code. See https://github.com/ncbi/deflake for more details
Home-page: http://packages.python.org/deflake
Author: NCBI
Author-email: UNKNOWN
License: Public Domain
Keywords: testing flaky
Platform: UNKNOWN
